sweetjwt/__init__.py
sweetjwt/authentication.py
sweetjwt/compat.py
sweetjwt/exceptions.py
sweetjwt/models.py
sweetjwt/serializers.py
sweetjwt/settings.py
sweetjwt/test.py
sweetjwt/utils.py
sweetjwt/views.py
djangosweet_jwt-0.0.1.dist-info/LICENSE
djangosweet_jwt-0.0.1.dist-info/METADATA
djangosweet_jwt-0.0.1.dist-info/WHEEL
djangosweet_jwt-0.0.1.dist-info/top_level.txt
djangosweet_jwt-0.0.1.dist-info/RECORD
